README
setup.py
htmlpetrol/__init__.py
htmlpetrol/render.py
htmlpetrol.egg-info/PKG-INFO
htmlpetrol.egg-info/SOURCES.txt
htmlpetrol.egg-info/dependency_links.txt
htmlpetrol.egg-info/top_level.txt