Metadata-Version: 1.0
Name: htmlpetrol
Version: 0.3-2
Summary: Apocalyptic HTML form procreator.
Home-page: UNKNOWN
Author: Derek McTavish Mounce
Author-email: d.mounce@silkseed.com
License: MIT
Platform: UNKNOWN
